flyingcircus/BitMask.py
flyingcircus/__init__.py
flyingcircus/_obsolete.py
flyingcircus/_version.py
flyingcircus/base.py
flyingcircus/extra.py
resources/__init__.py
flyingcircus-0.1.3.3.dist-info/AUTHORS.rst
flyingcircus-0.1.3.3.dist-info/LICENSE.rst
flyingcircus-0.1.3.3.dist-info/METADATA
flyingcircus-0.1.3.3.dist-info/WHEEL
flyingcircus-0.1.3.3.dist-info/entry_points.txt
flyingcircus-0.1.3.3.dist-info/top_level.txt
flyingcircus-0.1.3.3.dist-info/RECORD
