Metadata-Version: 2.1
Name: flyingcircus
Version: 0.1.3.3
Summary: Everything you always wanted to have in Python.*
Home-page: https://github.com/norok2/flyingcircus
Author: Riccardo Metere
Author-email: rick@metere.it
License: GPLv3+
Keywords: utils,misc,iterators,metaprogramming,science,mathematics,math,physics,format
Platform: UNKNOWN
Classifier: Development Status :: 3 - Alpha
Classifier: Environment :: Console
Classifier: Environment :: Other Environment
Classifier: Intended Audience :: Developers
Classifier: Intended Audience :: Information Technology
Classifier: Intended Audience :: System Administrators
Classifier: Intended Audience :: Science/Research
Classifier: License :: OSI Approved :: GNU General Public License v3 or later (GPLv3+)
Classifier: Natural Language :: English
Classifier: Operating System :: POSIX
Classifier: Operating System :: OS Independent
Classifier: Programming Language :: Python
Classifier: Programming Language :: Python :: 3
Classifier: Programming Language :: Python :: 3.6
Classifier: Topic :: Scientific/Engineering
Classifier: Topic :: Scientific/Engineering :: Mathematics
Classifier: Topic :: Scientific/Engineering :: Physics
Classifier: Topic :: Software Development
Classifier: Topic :: Software Development :: Libraries
Classifier: Topic :: System
Classifier: Topic :: Utilities
Requires-Dist: appdirs
Requires-Dist: blessed
Requires-Dist: setuptools
Requires-Dist: setuptools-scm
